skyshell/__init__.py
skyshell-2.1.dist-info/LICENSE.txt
skyshell-2.1.dist-info/METADATA
skyshell-2.1.dist-info/WHEEL
skyshell-2.1.dist-info/top_level.txt
skyshell-2.1.dist-info/RECORD
