Metadata-Version: 2.1
Name: skyshell
Version: 2.1
Home-page: https://github.com/Subdr2nk/Chatbot
Author: Caique Santos Carvalho
Author-email: subdr2nk@gmail.com
License: LICENSE.txt
Requires-Python: >= 3.8.0
License-File: LICENSE.txt
Requires-Dist: setuptools >=40.8.0
Requires-Dist: nltk >=0.4.6
